nickel/__init__.py
nickel/converters.py
nickel/managers.py
nickel/settings_utils.py
nickel/admin_utils/__init__.py
nickel/admin_utils/decorators.py
nickel/management/__init__.py
nickel/management/commands/__init__.py
nickel/management/commands/new_script.py
nickel/tables/__init__.py
nickel/tables/bootgrid.py
nickel/tables/jqgrid.py
nickel/templates/scripts/single_script.py.tpl
nickel-0.6.0.dist-info/METADATA
nickel-0.6.0.dist-info/RECORD
nickel-0.6.0.dist-info/WHEEL
nickel-0.6.0.dist-info/top_level.txt
